bin/build.sh
bin/clean.sh
bin/release.sh
gibson/api/BaseApi.py
gibson/api/Cli.py
gibson/api/DataApi.py
gibson/api/ProjectApi.py
gibson/bin/gibson.py
gibson/command/BaseCommand.py
gibson/command/Build.py
gibson/command/Conf.py
gibson/command/Count.py
gibson/command/Deploy.py
gibson/command/Dev.py
gibson/command/Forget.py
gibson/command/Help.py
gibson/command/Merge.py
gibson/command/Modify.py
gibson/command/Question.py
gibson/command/Remove.py
gibson/command/Show.py
gibson/command/Studio.py
gibson/command/Tree.py
gibson/command/Version.py
gibson/command/auth/Auth.py
gibson/command/auth/Login.py
gibson/command/auth/Logout.py
gibson/command/code/Api.py
gibson/command/code/Base.py
gibson/command/code/Code.py
gibson/command/code/Entity.py
gibson/command/code/Model.py
gibson/command/code/Models.py
gibson/command/code/Schema.py
gibson/command/code/Schemas.py
gibson/command/code/Test.py
gibson/command/code/Tests.py
gibson/command/importer/Import.py
gibson/command/importer/OpenApi.py
gibson/command/list/Entities.py
gibson/command/list/List.py
gibson/command/list/Projects.py
gibson/command/mcp/McpServer.py
gibson/command/new/Module.py
gibson/command/new/New.py
gibson/command/new/Project.py
gibson/command/rename/Entity.py
gibson/command/rename/Rename.py
gibson/command/rewrite/Rewrite.py
gibson/command/tests/test_command_BaseCommand.py
gibson/command/tests/test_command_Conf.py
gibson/conf/Api.py
gibson/conf/Code.py
gibson/conf/Custom.py
gibson/conf/Datastore.py
gibson/conf/Dependencies.py
gibson/conf/Dev.py
gibson/conf/Frameworks.py
gibson/conf/Modeler.py
gibson/conf/Paths.py
gibson/conf/Platform.py
gibson/conf/Project.py
gibson/conf/Version.py
gibson/conf/dev/Api.py
gibson/conf/dev/Base.py
gibson/conf/dev/Model.py
gibson/conf/dev/Schema.py
gibson/conf/tests/test_conf_Dependencies.py
gibson/conf/tests/test_conf_Platform.py
gibson/core/Colors.py
gibson/core/CommandRouter.py
gibson/core/Completions.py
gibson/core/Configuration.py
gibson/core/Conversation.py
gibson/core/Diff.py
gibson_cli-0.8.12.dist-info/METADATA
gibson_cli-0.8.12.dist-info/WHEEL
gibson_cli-0.8.12.dist-info/entry_points.txt
gibson_cli-0.8.12.dist-info/top_level.txt
gibson_cli-0.8.12.dist-info/RECORD
