Metadata-Version: 2.4
Name: gibson-cli
Version: 0.8.12
Summary: Gibson Command Line Interface
Author-email: GibsonAI <noc@gibsonai.com>
Project-URL: Homepage, https://gibsonai.com/
Project-URL: Documentation, https://docs.gibsonai.com/
Project-URL: Repository, https://github.com/gibsonai/cli
Project-URL: Issues, https://github.com/gibsonai/cli/issues
Project-URL: Changelog, https://github.com/gibsonai/cli/releases
Classifier: Operating System :: OS Independent
Classifier: Development Status :: 4 - Beta
Classifier: Intended Audience :: Developers
Classifier: Programming Language :: Python :: 3.10
Requires-Python: >=3.10
Requires-Dist: annotated-types==0.6.0
Requires-Dist: anyio==4.9.0
Requires-Dist: certifi==2024.2.2
Requires-Dist: charset-normalizer==3.3.2
Requires-Dist: click==8.1.7
Requires-Dist: dnspython==2.6.1
Requires-Dist: email-validator==2.1.1
Requires-Dist: exceptiongroup==1.2.0
Requires-Dist: faker==24.0.0
Requires-Dist: faker-sqlalchemy==0.10.2208140
Requires-Dist: fastapi==0.115.12
Requires-Dist: fastapi-cli==0.0.2
Requires-Dist: h11==0.14.0
Requires-Dist: harlequin==2.1.2
Requires-Dist: harlequin-mysql==1.1.0
Requires-Dist: httpcore==1.0.5
Requires-Dist: httptools==0.6.4
Requires-Dist: httpx==0.27.0
Requires-Dist: httpx-sse==0.4.0
Requires-Dist: idna==3.6
Requires-Dist: iniconfig==2.0.0
Requires-Dist: jinja2==3.1.4
Requires-Dist: markdown-it-py==3.0.0
Requires-Dist: markupsafe==2.1.5
Requires-Dist: mcp==1.6.0
Requires-Dist: mdurl==0.1.2
Requires-Dist: orjson==3.10.18
Requires-Dist: packaging==24.2
Requires-Dist: pluggy==1.4.0
Requires-Dist: pydantic==2.11.0
Requires-Dist: pydantic-core==2.33.0
Requires-Dist: pydantic-settings==2.8.1
Requires-Dist: pyfiglet==1.0.2
Requires-Dist: pygments==2.18.0
Requires-Dist: pymysql==1.1.0
Requires-Dist: pytest==8.0.1
Requires-Dist: python-dateutil==2.9.0.post0
Requires-Dist: python-dotenv==1.0.1
Requires-Dist: python-multipart==0.0.9
Requires-Dist: pyyaml==6.0.1
Requires-Dist: requests==2.31.0
Requires-Dist: rich==13.9.2
Requires-Dist: shellingham==1.5.4
Requires-Dist: six==1.16.0
Requires-Dist: sniffio==1.3.1
Requires-Dist: sqlalchemy==1.4.41
Requires-Dist: sse-starlette==2.2.1
Requires-Dist: starlette==0.46.1
Requires-Dist: textual==0.89.1
Requires-Dist: tomli==2.0.1
Requires-Dist: typer==0.12.3
Requires-Dist: typing-extensions==4.13.0
Requires-Dist: typing-inspection==0.4.0
Requires-Dist: ujson==5.9.0
Requires-Dist: urllib3==1.26.6
Requires-Dist: uvicorn==0.29.0
Requires-Dist: watchfiles==1.0.5
Requires-Dist: websockets==12.0
Requires-Dist: yaspin==3.1.0
